{"cameraMode":{"drawMode":0,"name":"Shaded","section":"Shading Mode"},"sceneLighting":true,"audioPlay":false,"sceneViewState":{"m_AlwaysRefresh":false,"showFog":true,"showSkybox":true,"showFlares":true,"showImageEffects":true,"showParticleSystems":true,"showVisualEffectGraphs":true,"m_FxEnabled":true},"in2DMode":false,"pivot":{"x":-19.573034286499025,"y":6.773301601409912,"z":6.9266676902771},"rotation":{"x":-0.35884714126586916,"y":0.0593041367828846,"z":-0.022852707654237748,"w":-0.9312343597412109},"size":0.8660253882408142,"orthographic":false}